{
  "indexes": [
    {
      "collectionGroup": "posts",
      "queryScope": "COLLECTION",
      "fields": [
        {
          "fieldPath": "categoryId",
          "order": "DESCENDING"
        },
        {
          "fieldPath": "createdAt",
          "order": "DESCENDING"
        }
      ]
    }
  ],
  "fieldOverrides": [
    {
      "collectionGroup": "profiles",
      "fieldPath": "ownerId",
      "indexes": [
        {
          "order": "ASCENDING",
          "queryScope": "COLLECTION"
        },
        {
          "order": "DESCENDING",
          "queryScope": "COLLECTION"
        },
        {
          "arrayConfig": "CONTAINS",
          "queryScope": "COLLECTION"
        }
      ]
    }
  ]
}
